jsonschematools/__init__.py
jsonschematools/core.py
jsonschematools/enums.py
jsonschematools-0.2.0.dist-info/METADATA
jsonschematools-0.2.0.dist-info/WHEEL
jsonschematools-0.2.0.dist-info/licenses/LICENSE
jsonschematools-0.2.0.dist-info/RECORD
