Metadata-Version: 2.1
Name: jsonschematools
Version: 0.2.0
Summary: Utilities for working with JSON Schema.
Project-URL: Repository, https://github.com/dmwyatt/jsonschematools
Author-email: Dustin Wyatt <dustin.wyatt@gmail.com>
License-File: LICENSE
Keywords: json,python,schema
Classifier: License :: OSI Approved :: MIT License
Classifier: Operating System :: OS Independent
Classifier: Programming Language :: Python :: 3
Requires-Python: >=3.11
Provides-Extra: test
Requires-Dist: pytest; extra == 'test'
